[
{
  "model": "administration.position",
  "pk": 10,
  "fields": {
    "pos_title": "CLERK",
    "pos_max": 1,
    "pos_group": null,
    "pos_category": "BARANGAY POSITION",
    "pos_is_predefined": true,
    "staff": "00001250924"
  }
},
{
  "model": "administration.position",
  "pk": 11,
  "fields": {
    "pos_title": "SECRETARY",
    "pos_max": 1,
    "pos_group": null,
    "pos_category": "BARANGAY POSITION",
    "pos_is_predefined": true,
    "staff": "00001250924"
  }
},
{
  "model": "administration.position",
  "pk": 12,
  "fields": {
    "pos_title": "TREASURER",
    "pos_max": 1,
    "pos_group": null,
    "pos_category": "BARANGAY POSITION",
    "pos_is_predefined": false,
    "staff": "00001250924"
  }
},
{
  "model": "administration.position",
  "pk": 13,
  "fields": {
    "pos_title": "GAD",
    "pos_max": 1,
    "pos_group": null,
    "pos_category": "BARANGAY POSITION",
    "pos_is_predefined": false,
    "staff": "00001250924"
  }
},
{
  "model": "administration.position",
  "pk": 14,
  "fields": {
    "pos_title": "WASTE HEAD",
    "pos_max": 1,
    "pos_group": "WASTE PERSONNEL",
    "pos_category": "BARANGAY POSITION",
    "pos_is_predefined": false,
    "staff": "00001250924"
  }
},
{
  "model": "administration.position",
  "pk": 15,
  "fields": {
    "pos_title": "LUPON SECRETARY",
    "pos_max": 1,
    "pos_group": "LUPON TAGAPAMAYAPA",
    "pos_category": "BARANGAY POSITION",
    "pos_is_predefined": false,
    "staff": "00001250924"
  }
},
{
  "model": "administration.position",
  "pk": 16,
  "fields": {
    "pos_title": "PEACE OFFICER",
    "pos_max": 1,
    "pos_group": null,
    "pos_category": "BARANGAY POSITION",
    "pos_is_predefined": false,
    "staff": "00001250924"
  }
},
{
  "model": "administration.position",
  "pk": 17,
  "fields": {
    "pos_title": "BPSO HEAD",
    "pos_max": 1,
    "pos_group": "BPSO",
    "pos_category": "BARANGAY POSITION",
    "pos_is_predefined": false,
    "staff": "00001250924"
  }
},
{
  "model": "administration.position",
  "pk": 18,
  "fields": {
    "pos_title": "BPSO MEMBER",
    "pos_max": 18,
    "pos_group": "BPSO",
    "pos_category": "BARANGAY POSITION",
    "pos_is_predefined": false,
    "staff": "00001250924"
  }
},
{
  "model": "administration.position",
  "pk": 1,
  "fields": {
    "pos_title": "ADMIN",
    "pos_max": 2,
    "pos_group": null,
    "pos_category": null,
    "pos_is_predefined": true,
    "staff": null
  }
},
{
  "model": "administration.position",
  "pk": 6,
  "fields": {
    "pos_title": "BARANGAY HEALTH WORKERS",
    "pos_max": 10,
    "pos_group": "HEALTH STAFFS",
    "pos_category": "HEALTH POSITION",
    "pos_is_predefined": true,
    "staff": null
  }
},
{
  "model": "administration.position",
  "pk": 7,
  "fields": {
    "pos_title": "DOCTOR",
    "pos_max": 1,
    "pos_group": "HEALTH STAFFS",
    "pos_category": "HEALTH POSITION",
    "pos_is_predefined": true,
    "staff": null
  }
},
{
  "model": "administration.position",
  "pk": 2,
  "fields": {
    "pos_title": "WATCHMAN",
    "pos_max": 5,
    "pos_group": "WASTE PERSONNEL",
    "pos_category": "BARANGAY POSITION",
    "pos_is_predefined": true,
    "staff": null
  }
},
{
  "model": "administration.position",
  "pk": 3,
  "fields": {
    "pos_title": "LOADER",
    "pos_max": 5,
    "pos_group": "WASTE PERSONNEL",
    "pos_category": "BARANGAY POSITION",
    "pos_is_predefined": true,
    "staff": null
  }
},
{
  "model": "administration.position",
  "pk": 5,
  "fields": {
    "pos_title": "DRIVER LOADER",
    "pos_max": 5,
    "pos_group": "WASTE PERSONNEL",
    "pos_category": "BARANGAY POSITION",
    "pos_is_predefined": true,
    "staff": null
  }
},
{
  "model": "administration.position",
  "pk": 8,
  "fields": {
    "pos_title": "SRF TEAM MEMBER",
    "pos_max": 5,
    "pos_group": "SAN ROQUE FIRE",
    "pos_category": "BARANGAY POSITION",
    "pos_is_predefined": true,
    "staff": null
  }
},
{
  "model": "administration.position",
  "pk": 9,
  "fields": {
    "pos_title": "SRF TEAM HEAD",
    "pos_max": 1,
    "pos_group": "SAN ROQUE FIRE",
    "pos_category": "BARANGAY POSITION",
    "pos_is_predefined": true,
    "staff": null
  }
}
]
